{
 "actions": [],
 "allow_rename": 1,
 "creation": "2023-03-07 08:38:59.103793",
 "doctype": "DocType",
 "editable_grid": 1,
 "engine": "InnoDB",
 "field_order": [
  "date",
  "week",
  "weight"
 ],
 "fields": [
  {
   "fieldname": "week",
   "fieldtype": "Int",
   "in_list_view": 1,
   "label": "Week"
  },
  {
   "fieldname": "date",
   "fieldtype": "Date",
   "in_list_view": 1,
   "label": "Date"
  },
  {
   "fieldname": "weight",
   "fieldtype": "Float",
   "in_list_view": 1,
   "label": "Weight"
  }
 ],
 "index_web_pages_for_search": 1,
 "istable": 1,
 "links": [],
 "modified": "2023-03-10 13:27:05.675987",
 "modified_by": "Administrator",
 "module": "Livestock Management",
 "name": "Weight",
 "owner": "Administrator",
 "permissions": [],
 "sort_field": "modified",
 "sort_order": "DESC"
}